dummy_package/__init__.py
dummy_test_package_vasumadaan-0.1.0.dist-info/licenses/LICENSE
dummy_test_package_vasumadaan-0.1.0.dist-info/METADATA
dummy_test_package_vasumadaan-0.1.0.dist-info/WHEEL
dummy_test_package_vasumadaan-0.1.0.dist-info/top_level.txt
dummy_test_package_vasumadaan-0.1.0.dist-info/RECORD
