Metadata-Version: 2.4
Name: dummy-test-package-vasumadaan
Version: 0.1.0
Summary: A dummy package for testing private PyPI index
Home-page: https://github.com/yourusername/dummy-package
Author: Vasu Madaan
Author-email: Vasu Madaan <vasu@example.com>
Classifier: Programming Language :: Python :: 3
Classifier: License :: OSI Approved :: MIT License
Classifier: Operating System :: OS Independent
Requires-Python: >=3.6
License-File: LICENSE
Dynamic: author
Dynamic: home-page
Dynamic: license-file
Dynamic: requires-python
